README.md
setup.py
cloudnsapi/__init__.py
cloudnsapi/api.py
cloudnsapi.egg-info/PKG-INFO
cloudnsapi.egg-info/SOURCES.txt
cloudnsapi.egg-info/dependency_links.txt
cloudnsapi.egg-info/requires.txt
cloudnsapi.egg-info/top_level.txt